CHANGES
LICENSE
MANIFEST.in
README.md
requirements.txt
setup.cfg
setup.py
examples/c-to-c.py
examples/cdecl.py
examples/explore_ast.py
examples/func_calls.py
examples/func_defs.py
examples/rewrite_ast.py
examples/using_cpp_libc.py
examples/using_gcc_E_libc.py
examples/c_files/funky.c
examples/c_files/hash.c
examples/c_files/memmgr.c
examples/c_files/memmgr.h
examples/c_files/year.c
py010parser/__init__.py
py010parser/_ast_gen.py
py010parser/_build_tables.py
py010parser/_c_ast.cfg
py010parser/ast_transforms.py
py010parser/c_ast.py
py010parser/c_generator.py
py010parser/c_lexer.py
py010parser/c_parser.py
py010parser/plyparser.py
py010parser.egg-info/PKG-INFO
py010parser.egg-info/SOURCES.txt
py010parser.egg-info/dependency_links.txt
py010parser.egg-info/requires.txt
py010parser.egg-info/top_level.txt
py010parser/ply/__init__.py
py010parser/ply/cpp.py
py010parser/ply/ctokens.py
py010parser/ply/lex.py
py010parser/ply/yacc.py
tests/all_tests.py
tests/test_basic_parse.py
tests/test_enum.py
tests/test_struct.py
utils/cpp.exe
utils/fake_libc_include/_ansi.h
utils/fake_libc_include/_fake_defines.h
utils/fake_libc_include/_fake_typedefs.h
utils/fake_libc_include/_syslist.h
utils/fake_libc_include/alloca.h
utils/fake_libc_include/ar.h
utils/fake_libc_include/argz.h
utils/fake_libc_include/assert.h
utils/fake_libc_include/complex.h
utils/fake_libc_include/ctype.h
utils/fake_libc_include/dirent.h
utils/fake_libc_include/envz.h
utils/fake_libc_include/errno.h
utils/fake_libc_include/fastmath.h
utils/fake_libc_include/fcntl.h
utils/fake_libc_include/fenv.h
utils/fake_libc_include/float.h
utils/fake_libc_include/getopt.h
utils/fake_libc_include/grp.h
utils/fake_libc_include/iconv.h
utils/fake_libc_include/ieeefp.h
utils/fake_libc_include/inttypes.h
utils/fake_libc_include/iso646.h
utils/fake_libc_include/langinfo.h
utils/fake_libc_include/libgen.h
utils/fake_libc_include/limits.h
utils/fake_libc_include/locale.h
utils/fake_libc_include/malloc.h
utils/fake_libc_include/math.h
utils/fake_libc_include/newlib.h
utils/fake_libc_include/paths.h
utils/fake_libc_include/process.h
utils/fake_libc_include/pthread.h
utils/fake_libc_include/pwd.h
