Metadata-Version: 1.2
Name: py010parser
Version: 0.1.15
Summary: 010 template parser in Python
Home-page: https://github.com/d0c-s4vage/py010parser
Author: James Johnson
Author-email: d0c.s4vage@gmail.com
Maintainer: James Johnson
License: BSD
Download-URL: https://github.com/d0c-s4vage/py010parser/tarball/v0.1.9
Keywords: 010,template,parser
Platform: Cross Platform
Classifier: Programming Language :: Python :: 2
Classifier: Programming Language :: Python :: 3
